{
  "data": [
    {
      "name": "Abin Joseph",
      "github": "https://github.com/abjs",
      "review": "Hack club kmea  is the one of the active club in kmea"
    },
    {
      "name": "Salman Nazeer",
      "github": "https://github.com/salmanselu",
      "review": "Hack Club is a great experience for me. Hack Club opened up many learning paths for me."
    },
    {
      "name": "Abin Joseph",
      "github": "https://github.com/abinjosephjosegiri",
      "review": "Hack club kmea  is the one of the active club in kmea"
    },
    {
      "name": "MUHAMMED RAEES",
      "github": "https://github.com/muhammedraeespy",
      "review": "Hack Club KMEA would be a great exposure opportunity for all."
    },
    {
      "name": "Jeethu Joshy",
      "github": "https://github.com/JeethuJoshy",
      "review": "Hack club is an awsome oppertunity for exploring technical skills and learning new things!"
    },
    {
      "name": "Anju Gopan",
      "github": "https://github.com/Anju-Gopan",
      "review": "Its Awesome !!"
    },
    {
      "name": "Pooja M P",
      "github": "https://github.com/poojamp48",
      "review": "Hack Club really helps in bringing out the best in me."
    },
    {
      "name": "Haripriya ks",
      "github": "https://github.com/Haripriya-ks",
      "review": "Its a great  opportunity."
    },
    {
      "name": "POOJA LAKSHMI",
      "github": "https://github.com/poojalaksmipk",
      "review": "hack club always try to be the best!"
    },
    {
      "name": "Athira Menon",
      "github": "https://github.com/athiramenon",
      "review": "Hack clubreally inspires me."
    },
    {
      "name": "Sandra Santhosh",
      "github": "https://github.com/sandrasanthosh31",
      "review": "Great opportunity"
    },
    {
      "name": "Jesna Siby",
      "github": "https://github.com/jesna424",
      "review": "Hack club kmea  is the one of the active club in kmea."
    },
    {
      "name": "Muhammed Shebeeb K M",
      "github": "https://github.com/mhdshebeeb",
      "review": "Hack club kmea  is a student community.its helps students to achieve their full potential,make their contribution to the communities"
    },
    {
      "name": "Farzana Khareem",
      "github": "https://github.com/farzanakhareem",
      "review": "It's a wonderful platform."
    },

    {
      "name": "Mansoor Majeed",
      "github": "https://github.com/Mans22r",
      "review": "Hack Club KMEA would be a great exposure opportunity for all. Gave awsome oppertunity for exploring technical skills and learning new things!"
    },
    {
      "name": "Maria Ashigha",
      "github": "https://github.com/MariaAshigha",
      "review": "It's an amazing platform."
    },
    {
      "name": "Shifana Abdul Azeez",
      "github": "https://github.com/shifana2506",
      "review": "It's a wonderful platform."
    },
    {
      "name": "Kashish S Shah",
      "github": "https://github.com/kashishshah12",
      "review": "Hack club Kmea  is an active student community which helps students to achieve their full potential,make their contribution to the communities"
    },
    {
      "name": "Mansoor Majeed",
      "github": "https://github.com/Mans22r",
      "review": "Hack Club KMEA would be a great exposure opportunity for all. Gave awsome oppertunity for exploring technical skills and learning new things!"
    },
    {
      "name": "Roushath Bevevi K S",
      "github": "https://github.com/Roushathbeeviks",
      "review": "Hackclub is a self learning platform"
    },
    {
      "name": "Raiz Antony",
      "github": "https://github.com/RAIZ05",
      "review": "Hackclub is a self learning and an amazing platform"
    },
    {
      "name": "Sahala P S",
      "github": "https://github.com/gitsahala",
      "review": "Its a good opportunity for me to learn the new skills."
    },
    {
      "name": "AnandaRaman C B",
      "github": "https://github.com/AnandaRaman9",
      "review": "Its a good opportunity for learning new skills."
    },
    {
      "name": "Aboobacker Shamil M",
      "github": "https://github.com/shamilabubacker7",
      "review": "I've been meaning learn something new ,hack club kmea gave a great opportunity to learn, and to be a part of a community . "
    },
    {
      "name": "Badusha",
      "github": "https://github.com/Badushaimthiyaz",
      "review": "let's learn together by using this amazing platform."
    },
    {
      "name": "Mohamed ashiq p",
      "github": "https://github.com/Ashiqmohd123",
      "review": "Hack club is a good opportunity."
    },
    {
      "name": "thaniya azhar",
      "github": "https://github.com/thaniya123",
      "review": "good opportunity."
    },
    {
      "name": "imrosh",
      "github": "https://github.com/imrosh",
      "review": "innovative space "
     {
      "name": "Ajmal E B",
      "github": "https://github.com/ajmaleb",
      "review": "Its a good opportunity for learning new skills."
    }
    
  ]
}
